demoExTest/__init__.py
demoExTest/database.py
demoExTest/database_operations.py
demoExTest/demo_db.db
demoExTest/main.py
demoExTest/main_window.py
demoExTest/material_form.py
demoExTest/materials_list.py
demoExTest/suppliers_tab.py
demoextest-1.0.dist-info/METADATA
demoextest-1.0.dist-info/WHEEL
demoextest-1.0.dist-info/top_level.txt
demoextest-1.0.dist-info/RECORD
