Metadata-Version: 2.4
Name: demoExTest
Version: 1.0
Requires-Dist: PyQt5
Dynamic: requires-dist
